ccrootpath/__init__.py
ccrootpath-1.1.dist-info/METADATA
ccrootpath-1.1.dist-info/WHEEL
ccrootpath-1.1.dist-info/top_level.txt
ccrootpath-1.1.dist-info/RECORD
