Metadata-Version: 2.1
Name: ccrootpath
Version: 1.1
Summary: Set project root path for importing local modules
Home-page: https://github.com/OpenFibers/CCRootPath
Author: OpenFibers
Author-email: openfibers@gmail.com
License: MIT
Platform: UNKNOWN
